tiegviet.py
tiegviet-0.0.1.dist-info/METADATA
tiegviet-0.0.1.dist-info/WHEEL
tiegviet-0.0.1.dist-info/top_level.txt
tiegviet-0.0.1.dist-info/RECORD
