Metadata-Version: 2.1
Name: tiegviet
Version: 0.0.1
Summary: Proposal version of Vietnamese by Prof Bui Hien
Home-page: UNKNOWN
Author: UNKNOWN
Author-email: UNKNOWN
License: UNKNOWN
Platform: UNKNOWN
